bdnd/__init__.py
bdnd/cli.py
bdnd/client.py
bdnd/config.py
bdnd/shell.py
bdnd-1.1.2.dist-info/LICENSE
bdnd-1.1.2.dist-info/METADATA
bdnd-1.1.2.dist-info/WHEEL
bdnd-1.1.2.dist-info/entry_points.txt
bdnd-1.1.2.dist-info/top_level.txt
bdnd-1.1.2.dist-info/RECORD
