Metadata-Version: 2.2
Name: bdnd
Version: 1.1.2
Summary: Baidu Netdisk Client - A Python client for Baidu Netdisk API with CLI support
Home-page: https://github.com/Rookie-Package/bdnd
Author: Rookie
Author-email: Rookie <RookieEmail@163.com>
License: MIT
Project-URL: Homepage, https://github.com/Rookie-Package/bdnd
Project-URL: Documentation, https://github.com/Rookie-Package/bdnd#readme
Project-URL: Repository, https://github.com/Rookie-Package/bdnd
Project-URL: Bug Reports, https://github.com/Rookie-Package/bdnd/issues
Keywords: baidu,netdisk,api,client,cli,upload,download
Classifier: Development Status :: 4 - Beta
Classifier: Intended Audience :: Developers
Classifier: Operating System :: OS Independent
Classifier: Programming Language :: Python :: 3
Classifier: Programming Language :: Python :: 3.7
Classifier: Programming Language :: Python :: 3.8
Classifier: Programming Language :: Python :: 3.9
Classifier: Programming Language :: Python :: 3.10
Classifier: Programming Language :: Python :: 3.11
Classifier: Programming Language :: Python :: 3.12
Requires-Python: >=3.7
License-File: LICENSE
Requires-Dist: requests>=2.25.0
Requires-Dist: tqdm>=4.60.0
Requires-Dist: urllib3>=1.26.0
Requires-Dist: env-key-manager>=0.1.0
Requires-Dist: tabulate>=0.9.0
Dynamic: author
Dynamic: home-page
Dynamic: requires-python
